{
  "resources": [
    {
      "path": "data.csv",
      "name": "data",
      "profile": "tabular-data-resource",
      "scheme": "file",
      "format": "csv",
      "hashing": "md5",
      "encoding": "utf-8",
      "schema": {
        "fields": [
          {
            "name": "SDG Series",
            "type": "string",
            "constraints": {
              "enum": [
                "",
                "Neonatal deaths (number) [3.2.2]",
                "Neonatal mortality rate [3.2.2]"
              ]
            },
            "title": "SDG Series"
          },
          {
            "name": "Unit of measure",
            "type": "string",
            "constraints": {
              "enum": [
                "",
                "Number",
                "Per 1,000 live births"
              ]
            },
            "title": "Unit of measure"
          },
          {
            "name": "Value",
            "type": "number",
            "title": "Value"
          },
          {
            "name": "Year",
            "type": "string",
            "title": "Year"
          }
        ]
      }
    }
  ],
  "profile": "data-package",
  "name": "3-2-2",
  "title": "Neonatal mortality rate"
}